nextcloud_mcp_server/__init__.py
nextcloud_mcp_server/app.py
nextcloud_mcp_server/auth/__init__.py
nextcloud_mcp_server/auth/bearer_auth.py
nextcloud_mcp_server/auth/client_registration.py
nextcloud_mcp_server/auth/context_helper.py
nextcloud_mcp_server/auth/token_verifier.py
nextcloud_mcp_server/client/__init__.py
nextcloud_mcp_server/client/base.py
nextcloud_mcp_server/client/calendar.py
nextcloud_mcp_server/client/contacts.py
nextcloud_mcp_server/client/cookbook.py
nextcloud_mcp_server/client/deck.py
nextcloud_mcp_server/client/groups.py
nextcloud_mcp_server/client/notes.py
nextcloud_mcp_server/client/sharing.py
nextcloud_mcp_server/client/tables.py
nextcloud_mcp_server/client/users.py
nextcloud_mcp_server/client/webdav.py
nextcloud_mcp_server/config.py
nextcloud_mcp_server/context.py
nextcloud_mcp_server/controllers/__init__.py
nextcloud_mcp_server/controllers/notes_search.py
nextcloud_mcp_server/models/__init__.py
nextcloud_mcp_server/models/base.py
nextcloud_mcp_server/models/calendar.py
nextcloud_mcp_server/models/contacts.py
nextcloud_mcp_server/models/cookbook.py
nextcloud_mcp_server/models/deck.py
nextcloud_mcp_server/models/notes.py
nextcloud_mcp_server/models/tables.py
nextcloud_mcp_server/models/users.py
nextcloud_mcp_server/models/webdav.py
nextcloud_mcp_server/server/__init__.py
nextcloud_mcp_server/server/calendar.py
nextcloud_mcp_server/server/contacts.py
nextcloud_mcp_server/server/cookbook.py
nextcloud_mcp_server/server/deck.py
nextcloud_mcp_server/server/notes.py
nextcloud_mcp_server/server/sharing.py
nextcloud_mcp_server/server/tables.py
nextcloud_mcp_server/server/webdav.py
nextcloud_mcp_server-0.17.1.dist-info/WHEEL
nextcloud_mcp_server-0.17.1.dist-info/entry_points.txt
nextcloud_mcp_server-0.17.1.dist-info/METADATA
nextcloud_mcp_server-0.17.1.dist-info/RECORD
