Metadata-Version: 2.3
Name: nextcloud-mcp-server
Version: 0.17.1
Summary: Model Context Protocol (MCP) server for Nextcloud integration - enables AI assistants to interact with Nextcloud data
Keywords: nextcloud,mcp,model-context-protocol,llm,ai,claude,webdav,caldav,carddav
Author: Chris Coutinho
Author-email: Chris Coutinho <chris@coutinho.io>
License: AGPL-3.0-only
Classifier: Development Status :: 4 - Beta
Classifier: Intended Audience :: Developers
Classifier: License :: OSI Approved :: GNU Affero General Public License v3
Classifier: Programming Language :: Python :: 3
Classifier: Programming Language :: Python :: 3.11
Classifier: Programming Language :: Python :: 3.12
Classifier: Topic :: Scientific/Engineering :: Artificial Intelligence
Classifier: Topic :: Communications
Classifier: Topic :: Internet :: WWW/HTTP
Requires-Dist: mcp[cli]>=1.18,<1.19
Requires-Dist: httpx>=0.28.1,<0.29.0
Requires-Dist: pillow>=12.0.0,<12.1.0
Requires-Dist: icalendar>=6.0.0,<7.0.0
Requires-Dist: pythonvcard4>=0.2.0
Requires-Dist: pydantic>=2.11.4
Requires-Dist: click>=8.1.8
Requires-Dist: caldav
Requires-Python: >=3.11
Project-URL: Bug Tracker, https://github.com/cbcoutinho/nextcloud-mcp-server/issues
Project-URL: Changelog, https://github.com/cbcoutinho/nextcloud-mcp-server/blob/master/CHANGELOG.md
Project-URL: Documentation, https://github.com/cbcoutinho/nextcloud-mcp-server#readme
Project-URL: Homepage, https://github.com/cbcoutinho/nextcloud-mcp-server
Project-URL: Repository, https://github.com/cbcoutinho/nextcloud-mcp-server
